pyhyperworks.py
_cccPartLib/__init__.py
_clientConfig/__init__.py
_images/__init__.py
_materialLib/__init__.py
_meshStandrad/__init__.py
_utils/__init__.py
loadcase/__init__.py
loadcase/lc_fender_gload.py
loadcase/lc_fender_modal.py
modeling/PropNamedByPID.py
modeling/__init__.py
modeling/pre_modeling_LoadCAD.py
pyhyperworks-1.0.0.dist-info/LICENSE
pyhyperworks-1.0.0.dist-info/METADATA
pyhyperworks-1.0.0.dist-info/WHEEL
pyhyperworks-1.0.0.dist-info/top_level.txt
pyhyperworks-1.0.0.dist-info/RECORD
