Metadata-Version: 2.2
Name: pyhyperworks
Version: 1.0.0
Summary: This package is a tools-package for Altair HyperWorks
Home-page: https://github.com/zxx4477/pyhyperworks
Author: xinxing.zhang
Author-email: zxx4477@126.com
License: MIT
License-File: LICENSE
Dynamic: author
Dynamic: author-email
Dynamic: home-page
Dynamic: license
Dynamic: summary
